LICENSE
MANIFEST.in
Makefile
README
setup.py
markdown_checklist/__init__.py
markdown_checklist/checklists.js
markdown_checklist/extension.py
markdown_checklist.egg-info/PKG-INFO
markdown_checklist.egg-info/SOURCES.txt
markdown_checklist.egg-info/dependency_links.txt
markdown_checklist.egg-info/not-zip-safe
markdown_checklist.egg-info/requires.txt
markdown_checklist.egg-info/top_level.txt
test/__init__.py
test/test_customization.py
test/test_main.py
test/__pycache__/__init__.cpython-39.pyc
test/__pycache__/test_customization.cpython-39-pytest-7.1.2.pyc
test/__pycache__/test_main.cpython-39-pytest-7.1.2.pyc