Metadata-Version: 2.1
Name: markdown-checklist
Version: 0.4.4
Summary: Python Markdown extension for task lists with checkboxes
Home-page: https://github.com/FND/markdown-checklist
Author: FND
Author-email: 
Maintainer: FND
License: MIT
Platform: Posix; MacOS X; Windows
Provides-Extra: testing
Provides-Extra: coverage
License-File: LICENSE
